{"statusCode": 200, "headers": {"Content-Type": "application/json", "Access-Control-Allow-Origin": "*"}, "body": "{\"user_id\": \"test_farmer_001\", \"query\": \"What are the current market prices for tomatoes?\", \"response\": \"**Market Information: Current Tomato Prices in Nashik, Maharashtra (Estimated)**\\n\\nGiven that the live market data for tomatoes is currently unavailable, I will provide estimated prices based on recent market trends. Please note that these are estimates and actual prices may vary.\\n\\n- **Estimated Price Range for Tomatoes in Nashik**: \\u20b930 to \\u20b950 per kilogram\\n- **Nearby Mandis**: Dindori, Igatpuri, Sinnar\\n\\n**Tips for Selling Your Produce:**\\n- Check with local traders or cooperatives for more accurate pricing.\\n- Visit nearby mandis to compare prices and get the best deal for your tomatoes.\\n- Consider forming a farmers' group to negotiate better prices collectively.\\n\\nIf you need more precise market information or have other queries, feel free to ask!\\n\", \"agent_used\": \"supervisor\", \"metadata\": {\"hashed_ip\": null}, \"timestamp\": \"2026-03-05T20:29:04.244831\"}"}